squall/__init__.py
squall/applications.py
squall/bindings.py
squall/compression.py
squall/concurrency.py
squall/convertors.py
squall/datastructures.py
squall/errors.py
squall/exception_handlers.py
squall/exceptions.py
squall/handlers.py
squall/lifespan.py
squall/logger.py
squall/params.py
squall/py.typed
squall/requests.py
squall/responses.py
squall/staticfiles.py
squall/templating.py
squall/testclient.py
squall/types.py
squall/utils.py
squall/websockets.py
squall/middleware/__init__.py
squall/middleware/cors.py
squall/middleware/httpsredirect.py
squall/middleware/trustedhost.py
squall/middleware/wsgi.py
squall/openapi/__init__.py
squall/openapi/constants.py
squall/openapi/docs.py
squall/openapi/utils.py
squall/routing/__init__.py
squall/routing/path.py
squall/routing/router.py
squall/routing/routes.py
squall/routing/utils.py
squall/tracing/__init__.py
squall/tracing/constants.py
squall/tracing/helpers.py
squall/validators/__init__.py
squall/validators/ast_helpers.py
squall/validators/head.py
python_squall-0.3.0.dist-info/LICENSE
python_squall-0.3.0.dist-info/WHEEL
python_squall-0.3.0.dist-info/METADATA
python_squall-0.3.0.dist-info/RECORD
