Metadata-Version: 2.1
Name: python-squall
Version: 0.3.0
Summary: Squall ASGI REST framework
Author-email: Stanislav Dubrovskyi <s.dubrovskyi@cleverdec.com>
Maintainer-email: Stanislav Dubrovskyi <s.dubrovskyi@cleverdec.com>, Vitalii Kovalchuk <naviot96@gmail.com>, Svitlana Kost <s.kost@cleverdec.com>
Requires-Python: >=3.9.0
Classifier: Intended Audience :: Information Technology
Classifier: Intended Audience :: System Administrators
Classifier: Operating System :: OS Independent
Classifier: Programming Language :: Python :: 3
Classifier: Programming Language :: Python
Classifier: Topic :: Internet
Classifier: Topic :: Software Development :: Libraries :: Application Frameworks
Classifier: Topic :: Software Development :: Libraries :: Python Modules
Classifier: Topic :: Software Development :: Libraries
Classifier: Topic :: Software Development
Classifier: Typing :: Typed
Classifier: Development Status :: 4 - Beta
Classifier: Environment :: Web Environment
Classifier: Framework :: AsyncIO
Classifier: Intended Audience :: Developers
Classifier: License :: OSI Approved :: MIT License
Classifier: Programming Language :: Python :: 3 :: Only
Classifier: Programming Language :: Python :: 3.9
Classifier: Topic :: Internet :: WWW/HTTP :: HTTP Servers
Classifier: Topic :: Internet :: WWW/HTTP
Requires-Dist: squall-router ==0.1.1
Requires-Dist: starlette ==0.16.0
Requires-Dist: orjson >=3.6.4,<4.0.0
Requires-Dist: apischema >=0.17.0,<1.0.0
Requires-Dist: isal >=0.11.1,<1.0.0
Requires-Dist: requests >=2.24.0,<3.0.0 ; extra == "all"
Requires-Dist: jinja2 >=2.11.2,<4.0.0 ; extra == "all"
Requires-Dist: python-multipart >=0.0.5,<0.0.6 ; extra == "all"
Requires-Dist: itsdangerous >=1.1.0,<3.0.0 ; extra == "all"
Requires-Dist: pyyaml >=5.3.1,<6.0.0 ; extra == "all"
Requires-Dist: orjson >=3.6.4,<4.0.0 ; extra == "all"
Requires-Dist: email_validator >=1.1.1,<2.0.0 ; extra == "all"
Requires-Dist: uvicorn[standard] >=0.12.0,<0.16.0 ; extra == "all"
Requires-Dist: python-jose[cryptography] >=3.3.0,<4.0.0 ; extra == "dev"
Requires-Dist: passlib[bcrypt] >=1.7.2,<2.0.0 ; extra == "dev"
Requires-Dist: autoflake >=1.4.0,<2.0.0 ; extra == "dev"
Requires-Dist: flake8 >=3.8.3,<4.0.0 ; extra == "dev"
Requires-Dist: uvicorn[standard] >=0.12.0,<0.16.0 ; extra == "dev"
Requires-Dist: mkdocs >=1.1.2,<2.0.0 ; extra == "doc"
Requires-Dist: mkdocs-material >=7.1.9,<8.0.0 ; extra == "doc"
Requires-Dist: mdx-include >=1.4.1,<2.0.0 ; extra == "doc"
Requires-Dist: mkdocs-markdownextradata-plugin >=0.1.7,<0.3.0 ; extra == "doc"
Requires-Dist: typer-cli >=0.0.12,<0.0.13 ; extra == "doc"
Requires-Dist: pyyaml >=5.3.1,<6.0.0 ; extra == "doc"
Requires-Dist: pydantic >=1.8.2,<2.0.0 ; extra == "doc"
Requires-Dist: pytest >=6.2.4,<7.0.0 ; extra == "test"
Requires-Dist: pytest-cov >=2.12.0,<4.0.0 ; extra == "test"
Requires-Dist: pytest-mock >=3.6.1,<4.0.0 ; extra == "test"
Requires-Dist: mypy ==0.910 ; extra == "test"
Requires-Dist: flake8 >=3.8.3,<4.0.0 ; extra == "test"
Requires-Dist: black ==21.9b0 ; extra == "test"
Requires-Dist: isort >=5.0.6,<6.0.0 ; extra == "test"
Requires-Dist: requests >=2.24.0,<3.0.0 ; extra == "test"
Requires-Dist: httpx >=0.14.0,<0.19.0 ; extra == "test"
Requires-Dist: email_validator >=1.1.1,<2.0.0 ; extra == "test"
Requires-Dist: sqlalchemy >=1.3.18,<1.5.0 ; extra == "test"
Requires-Dist: peewee >=3.13.3,<4.0.0 ; extra == "test"
Requires-Dist: databases[sqlite] >=0.3.2,<0.6.0 ; extra == "test"
Requires-Dist: python-multipart >=0.0.5,<0.0.6 ; extra == "test"
Requires-Dist: flask >=1.1.2,<3.0.0 ; extra == "test"
Requires-Dist: anyio[trio] >=3.2.1,<4.0.0 ; extra == "test"
Requires-Dist: types-orjson ==3.6.0 ; extra == "test"
Requires-Dist: types-dataclasses ==0.1.7 ; extra == "test" and ( python_version<'3.7')
Project-URL: Documentation, https://github.com/mtag-dev/squall
Project-URL: Source, https://github.com/mtag-dev/squall
Provides-Extra: all
Provides-Extra: dev
Provides-Extra: doc
Provides-Extra: test
